{
  "openapi": "3.0.4",
  "info": {
    "title": "Queue OpenAPI for fal-ai/elevenlabs/text-to-dialogue/eleven-v3",
    "version": "1.0.0",
    "description": "The OpenAPI schema for the fal-ai/elevenlabs/text-to-dialogue/eleven-v3 queue.",
    "x-fal-metadata": {
      "endpointId": "fal-ai/elevenlabs/text-to-dialogue/eleven-v3",
      "category": "text-to-audio",
      "thumbnailUrl": "https://fal.media/files/panda/twZsKdCTiF8JXv-rRcPZu_8414166d52a548859a8df01bf720fe46.jpg",
      "playgroundUrl": "https://fal.ai/models/fal-ai/elevenlabs/text-to-dialogue/eleven-v3",
      "documentationUrl": "https://fal.ai/models/fal-ai/elevenlabs/text-to-dialogue/eleven-v3/api"
    }
  },
  "components": {
    "securitySchemes": {
      "apiKeyAuth": {
        "type": "apiKey",
        "in": "header",
        "name": "Authorization",
        "description": "Fal Key"
      }
    },
    "schemas": {
      "QueueStatus": {
        "type": "object",
        "properties": {
          "status": {
            "type": "string",
            "enum": [
              "IN_QUEUE",
              "IN_PROGRESS",
              "COMPLETED"
            ]
          },
          "request_id": {
            "type": "string",
            "description": "The request id."
          },
          "response_url": {
            "type": "string",
            "description": "The response url."
          },
          "status_url": {
            "type": "string",
            "description": "The status url."
          },
          "cancel_url": {
            "type": "string",
            "description": "The cancel url."
          },
          "logs": {
            "type": "object",
            "description": "The logs.",
            "additionalProperties": true
          },
          "metrics": {
            "type": "object",
            "description": "The metrics.",
            "additionalProperties": true
          },
          "queue_position": {
            "type": "integer",
            "description": "The queue position."
          }
        },
        "required": [
          "status",
          "request_id"
        ]
      },
      "ElevenlabsTextToDialogueElevenV3Input": {
        "x-fal-order-properties": [
          "inputs",
          "stability",
          "use_speaker_boost",
          "pronunciation_dictionary_locators",
          "seed",
          "language_code"
        ],
        "type": "object",
        "properties": {
          "stability": {
            "anyOf": [
              {
                "minimum": 0,
                "maximum": 1,
                "type": "number"
              },
              {
                "type": "null"
              }
            ],
            "description": "Determines how stable the voice is and the randomness between each generation. Lower values introduce broader emotional range for the voice. Higher values can result in a monotonous voice with limited emotion. Must be one of 0.0, 0.5, 1.0, else it will be rounded to the nearest value.",
            "title": "Stability"
          },
          "inputs": {
            "examples": [
              [
                {
                  "text": "[applause] Thank you all for coming tonight! Today we have a very special guest with us.",
                  "voice": "Aria"
                },
                {
                  "text": "[gulps] ... [strong canadian accent] [excited] Hello everyone! Thank you all for having me tonight on this special day.",
                  "voice": "Charlotte"
                }
              ]
            ],
            "description": "A list of dialogue inputs, each containing text and a voice ID which will be converted into speech.",
            "type": "array",
            "title": "Inputs",
            "items": {
              "$ref": "#/components/schemas/DialogueBlock"
            }
          },
          "language_code": {
            "anyOf": [
              {
                "type": "string"
              },
              {
                "type": "null"
              }
            ],
            "description": "Language code (ISO 639-1) used to enforce a language for the model. An error will be returned if language code is not supported by the model.",
            "title": "Language Code"
          },
          "seed": {
            "anyOf": [
              {
                "type": "integer"
              },
              {
                "type": "null"
              }
            ],
            "description": "Random seed for reproducibility.",
            "title": "Seed"
          },
          "use_speaker_boost": {
            "anyOf": [
              {
                "type": "boolean"
              },
              {
                "type": "null"
              }
            ],
            "description": "This setting boosts the similarity to the original speaker. Using this setting requires a slightly higher computational load, which in turn increases latency.",
            "title": "Use Speaker Boost"
          },
          "pronunciation_dictionary_locators": {
            "description": "A list of pronunciation dictionary locators (id, version_id) to be applied to the text. They will be applied in order. You may have up to 3 locators per request",
            "type": "array",
            "title": "Pronunciation Dictionary Locators",
            "items": {
              "$ref": "#/components/schemas/PronunciationDictionaryLocator"
            },
            "default": []
          }
        },
        "title": "TextToDialogueRequest",
        "required": [
          "inputs"
        ]
      },
      "ElevenlabsTextToDialogueElevenV3Output": {
        "x-fal-order-properties": [
          "audio",
          "seed"
        ],
        "type": "object",
        "properties": {
          "seed": {
            "description": "Random seed for reproducibility.",
            "type": "integer",
            "title": "Seed"
          },
          "audio": {
            "examples": [
              {
                "url": "https://v3.fal.media/files/zebra/XFeGS8Fq-q1eAPG2sSAo__output.mp3"
              }
            ],
            "description": "The generated audio file",
            "$ref": "#/components/schemas/File"
          }
        },
        "title": "TextToDialogueOutput",
        "required": [
          "audio",
          "seed"
        ]
      },
      "DialogueBlock": {
        "x-fal-order-properties": [
          "text",
          "voice"
        ],
        "type": "object",
        "properties": {
          "text": {
            "description": "The dialogue text",
            "type": "string",
            "title": "Text"
          },
          "voice": {
            "examples": [
              "Aria",
              "Roger",
              "Sarah",
              "Laura",
              "Charlie",
              "George",
              "Callum",
              "River",
              "Liam",
              "Charlotte",
              "Alice",
              "Matilda",
              "Will",
              "Jessica",
              "Eric",
              "Chris",
              "Brian",
              "Daniel",
              "Lily",
              "Bill"
            ],
            "description": "The name or the ID of the voice to be used for the generation.",
            "type": "string",
            "title": "Voice"
          }
        },
        "title": "DialogueBlock",
        "required": [
          "text",
          "voice"
        ]
      },
      "PronunciationDictionaryLocator": {
        "x-fal-order-properties": [
          "pronunciation_dictionary_id",
          "version_id"
        ],
        "type": "object",
        "properties": {
          "version_id": {
            "anyOf": [
              {
                "type": "string"
              },
              {
                "type": "null"
              }
            ],
            "description": "The ID of the version of the pronunciation dictionary. If not provided, the latest version will be used.",
            "title": "Version Id"
          },
          "pronunciation_dictionary_id": {
            "anyOf": [
              {
                "type": "string"
              },
              {
                "type": "null"
              }
            ],
            "description": "The ID of the pronunciation dictionary.",
            "title": "Pronunciation Dictionary Id"
          }
        },
        "title": "PronunciationDictionaryLocator"
      },
      "File": {
        "x-fal-order-properties": [
          "url",
          "content_type",
          "file_name",
          "file_size"
        ],
        "type": "object",
        "properties": {
          "file_size": {
            "examples": [
              4404019
            ],
            "description": "The size of the file in bytes.",
            "anyOf": [
              {
                "type": "integer"
              },
              {
                "type": "null"
              }
            ],
            "title": "File Size"
          },
          "file_name": {
            "examples": [
              "z9RV14K95DvU.png"
            ],
            "description": "The name of the file. It will be auto-generated if not provided.",
            "anyOf": [
              {
                "type": "string"
              },
              {
                "type": "null"
              }
            ],
            "title": "File Name"
          },
          "content_type": {
            "examples": [
              "image/png"
            ],
            "description": "The mime type of the file.",
            "anyOf": [
              {
                "type": "string"
              },
              {
                "type": "null"
              }
            ],
            "title": "Content Type"
          },
          "url": {
            "description": "The URL where the file can be downloaded from.",
            "type": "string",
            "title": "Url"
          }
        },
        "title": "File",
        "required": [
          "url"
        ]
      }
    }
  },
  "paths": {
    "/fal-ai/elevenlabs/text-to-dialogue/eleven-v3/requests/{request_id}/status": {
      "get": {
        "parameters": [
          {
            "name": "request_id",
            "in": "path",
            "required": true,
            "schema": {
              "type": "string",
              "description": "Request ID"
            }
          },
          {
            "name": "logs",
            "in": "query",
            "required": false,
            "schema": {
              "type": "number",
              "description": "Whether to include logs (`1`) in the response or not (`0`)."
            }
          }
        ],
        "responses": {
          "200": {
            "description": "The request status.",
            "content": {
              "application/json": {
                "schema": {
                  "$ref": "#/components/schemas/QueueStatus"
                }
              }
            }
          }
        }
      }
    },
    "/fal-ai/elevenlabs/text-to-dialogue/eleven-v3/requests/{request_id}/cancel": {
      "put": {
        "parameters": [
          {
            "name": "request_id",
            "in": "path",
            "required": true,
            "schema": {
              "type": "string",
              "description": "Request ID"
            }
          }
        ],
        "responses": {
          "200": {
            "description": "The request was cancelled.",
            "content": {
              "application/json": {
                "schema": {
                  "type": "object",
                  "properties": {
                    "success": {
                      "type": "boolean",
                      "description": "Whether the request was cancelled successfully."
                    }
                  }
                }
              }
            }
          }
        }
      }
    },
    "/fal-ai/elevenlabs/text-to-dialogue/eleven-v3": {
      "post": {
        "requestBody": {
          "required": true,
          "content": {
            "application/json": {
              "schema": {
                "$ref": "#/components/schemas/ElevenlabsTextToDialogueElevenV3Input"
              }
            }
          }
        },
        "responses": {
          "200": {
            "description": "The request status.",
            "content": {
              "application/json": {
                "schema": {
                  "$ref": "#/components/schemas/QueueStatus"
                }
              }
            }
          }
        }
      }
    },
    "/fal-ai/elevenlabs/text-to-dialogue/eleven-v3/requests/{request_id}": {
      "get": {
        "parameters": [
          {
            "name": "request_id",
            "in": "path",
            "required": true,
            "schema": {
              "type": "string",
              "description": "Request ID"
            }
          }
        ],
        "responses": {
          "200": {
            "description": "Result of the request.",
            "content": {
              "application/json": {
                "schema": {
                  "$ref": "#/components/schemas/ElevenlabsTextToDialogueElevenV3Output"
                }
              }
            }
          }
        }
      }
    }
  },
  "servers": [
    {
      "url": "https://queue.fal.run"
    }
  ],
  "security": [
    {
      "apiKeyAuth": []
    }
  ]
}