{
  "openapi": "3.0.4",
  "info": {
    "title": "Queue OpenAPI for fal-ai/fashn/tryon/v1.5",
    "version": "1.0.0",
    "description": "The OpenAPI schema for the fal-ai/fashn/tryon/v1.5 queue.",
    "x-fal-metadata": {
      "endpointId": "fal-ai/fashn/tryon/v1.5",
      "category": "image-to-image",
      "thumbnailUrl": "https://storage.googleapis.com/falserverless/gallery/fashn_wide.webp",
      "playgroundUrl": "https://fal.ai/models/fal-ai/fashn/tryon/v1.5",
      "documentationUrl": "https://fal.ai/models/fal-ai/fashn/tryon/v1.5/api"
    }
  },
  "components": {
    "securitySchemes": {
      "apiKeyAuth": {
        "type": "apiKey",
        "in": "header",
        "name": "Authorization",
        "description": "Fal Key"
      }
    },
    "schemas": {
      "QueueStatus": {
        "type": "object",
        "properties": {
          "status": {
            "type": "string",
            "enum": [
              "IN_QUEUE",
              "IN_PROGRESS",
              "COMPLETED"
            ]
          },
          "request_id": {
            "type": "string",
            "description": "The request id."
          },
          "response_url": {
            "type": "string",
            "description": "The response url."
          },
          "status_url": {
            "type": "string",
            "description": "The status url."
          },
          "cancel_url": {
            "type": "string",
            "description": "The cancel url."
          },
          "logs": {
            "type": "object",
            "description": "The logs.",
            "additionalProperties": true
          },
          "metrics": {
            "type": "object",
            "description": "The metrics.",
            "additionalProperties": true
          },
          "queue_position": {
            "type": "integer",
            "description": "The queue position."
          }
        },
        "required": [
          "status",
          "request_id"
        ]
      },
      "FashnTryonV15Input": {
        "x-fal-order-properties": [
          "model_image",
          "garment_image",
          "category",
          "mode",
          "garment_photo_type",
          "moderation_level",
          "seed",
          "num_samples",
          "segmentation_free",
          "sync_mode",
          "output_format"
        ],
        "type": "object",
        "properties": {
          "model_image": {
            "examples": [
              "https://utfs.io/f/wXFHUNfTHmLj4prvqbRMQ6JXFyUr3IT0avK2HSOmZWiAsxg9"
            ],
            "description": "URL or base64 of the model image",
            "type": "string",
            "title": "Model Image"
          },
          "moderation_level": {
            "enum": [
              "none",
              "permissive",
              "conservative"
            ],
            "description": "Content moderation level for garment images. 'none' disables moderation, 'permissive' blocks only explicit content, 'conservative' also blocks underwear and swimwear.",
            "type": "string",
            "title": "Moderation Level",
            "default": "permissive"
          },
          "garment_photo_type": {
            "enum": [
              "auto",
              "model",
              "flat-lay"
            ],
            "description": "Specifies the type of garment photo to optimize internal parameters for better performance. 'model' is for photos of garments on a model, 'flat-lay' is for flat-lay or ghost mannequin images, and 'auto' attempts to automatically detect the photo type.",
            "type": "string",
            "title": "Garment Photo Type",
            "default": "auto"
          },
          "garment_image": {
            "examples": [
              "https://utfs.io/f/wXFHUNfTHmLjtkhepmqOUnkr8XxZbNIFmRWldShDLu320TeC"
            ],
            "description": "URL or base64 of the garment image",
            "type": "string",
            "title": "Garment Image"
          },
          "category": {
            "enum": [
              "tops",
              "bottoms",
              "one-pieces",
              "auto"
            ],
            "description": "Category of the garment to try-on. 'auto' will attempt to automatically detect the category of the garment.",
            "type": "string",
            "title": "Category",
            "default": "auto"
          },
          "sync_mode": {
            "description": "If `True`, the media will be returned as a data URI and the output data won't be available in the request history.",
            "type": "boolean",
            "title": "Sync Mode",
            "default": false
          },
          "segmentation_free": {
            "description": "Disables human parsing on the model image.",
            "type": "boolean",
            "title": "Segmentation Free",
            "default": true
          },
          "num_samples": {
            "minimum": 1,
            "description": "Number of images to generate in a single run. Image generation has a random element in it, so trying multiple images at once increases the chances of getting a good result.",
            "type": "integer",
            "maximum": 4,
            "title": "Num Samples",
            "default": 1
          },
          "mode": {
            "enum": [
              "performance",
              "balanced",
              "quality"
            ],
            "description": "Specifies the mode of operation. 'performance' mode is faster but may sacrifice quality, 'balanced' mode is a balance between speed and quality, and 'quality' mode is slower but produces higher quality results.",
            "type": "string",
            "title": "Mode",
            "default": "balanced"
          },
          "seed": {
            "anyOf": [
              {
                "type": "integer"
              },
              {
                "type": "null"
              }
            ],
            "description": "Sets random operations to a fixed state. Use the same seed to reproduce results with the same inputs, or different seed to force different results.",
            "title": "Seed"
          },
          "output_format": {
            "enum": [
              "png",
              "jpeg"
            ],
            "description": "Output format of the generated images. 'png' is highest quality, while 'jpeg' is faster",
            "type": "string",
            "title": "Output Format",
            "default": "png"
          }
        },
        "title": "Input",
        "required": [
          "model_image",
          "garment_image"
        ]
      },
      "FashnTryonV15Output": {
        "x-fal-order-properties": [
          "images"
        ],
        "type": "object",
        "properties": {
          "images": {
            "examples": [
              [
                {
                  "url": "https://cdn.staging.fashn.ai/464eeeb1-4faa-4a2d-8c17-342d0d35c4c1/output_0.png"
                }
              ]
            ],
            "title": "Images",
            "type": "array",
            "items": {
              "$ref": "#/components/schemas/File"
            }
          }
        },
        "title": "Output",
        "required": [
          "images"
        ]
      },
      "File": {
        "x-fal-order-properties": [
          "url",
          "content_type",
          "file_name",
          "file_size"
        ],
        "type": "object",
        "properties": {
          "file_size": {
            "anyOf": [
              {
                "type": "integer"
              },
              {
                "type": "null"
              }
            ],
            "description": "The size of the file in bytes.",
            "examples": [
              4404019
            ],
            "title": "File Size"
          },
          "file_name": {
            "anyOf": [
              {
                "type": "string"
              },
              {
                "type": "null"
              }
            ],
            "description": "The name of the file. It will be auto-generated if not provided.",
            "examples": [
              "z9RV14K95DvU.png"
            ],
            "title": "File Name"
          },
          "content_type": {
            "anyOf": [
              {
                "type": "string"
              },
              {
                "type": "null"
              }
            ],
            "description": "The mime type of the file.",
            "examples": [
              "image/png"
            ],
            "title": "Content Type"
          },
          "url": {
            "description": "The URL where the file can be downloaded from.",
            "type": "string",
            "title": "Url"
          }
        },
        "title": "File",
        "required": [
          "url"
        ]
      }
    }
  },
  "paths": {
    "/fal-ai/fashn/tryon/v1.5/requests/{request_id}/status": {
      "get": {
        "parameters": [
          {
            "name": "request_id",
            "in": "path",
            "required": true,
            "schema": {
              "type": "string",
              "description": "Request ID"
            }
          },
          {
            "name": "logs",
            "in": "query",
            "required": false,
            "schema": {
              "type": "number",
              "description": "Whether to include logs (`1`) in the response or not (`0`)."
            }
          }
        ],
        "responses": {
          "200": {
            "description": "The request status.",
            "content": {
              "application/json": {
                "schema": {
                  "$ref": "#/components/schemas/QueueStatus"
                }
              }
            }
          }
        }
      }
    },
    "/fal-ai/fashn/tryon/v1.5/requests/{request_id}/cancel": {
      "put": {
        "parameters": [
          {
            "name": "request_id",
            "in": "path",
            "required": true,
            "schema": {
              "type": "string",
              "description": "Request ID"
            }
          }
        ],
        "responses": {
          "200": {
            "description": "The request was cancelled.",
            "content": {
              "application/json": {
                "schema": {
                  "type": "object",
                  "properties": {
                    "success": {
                      "type": "boolean",
                      "description": "Whether the request was cancelled successfully."
                    }
                  }
                }
              }
            }
          }
        }
      }
    },
    "/fal-ai/fashn/tryon/v1.5": {
      "post": {
        "requestBody": {
          "required": true,
          "content": {
            "application/json": {
              "schema": {
                "$ref": "#/components/schemas/FashnTryonV15Input"
              }
            }
          }
        },
        "responses": {
          "200": {
            "description": "The request status.",
            "content": {
              "application/json": {
                "schema": {
                  "$ref": "#/components/schemas/QueueStatus"
                }
              }
            }
          }
        }
      }
    },
    "/fal-ai/fashn/tryon/v1.5/requests/{request_id}": {
      "get": {
        "parameters": [
          {
            "name": "request_id",
            "in": "path",
            "required": true,
            "schema": {
              "type": "string",
              "description": "Request ID"
            }
          }
        ],
        "responses": {
          "200": {
            "description": "Result of the request.",
            "content": {
              "application/json": {
                "schema": {
                  "$ref": "#/components/schemas/FashnTryonV15Output"
                }
              }
            }
          }
        }
      }
    }
  },
  "servers": [
    {
      "url": "https://queue.fal.run"
    }
  ],
  "security": [
    {
      "apiKeyAuth": []
    }
  ]
}